odoo/addons/so_line_description_picking/README.rst
odoo/addons/so_line_description_picking/__init__.py
odoo/addons/so_line_description_picking/__manifest__.py
odoo/addons/so_line_description_picking/models/__init__.py
odoo/addons/so_line_description_picking/models/sale_order_line.py
odoo/addons/so_line_description_picking/models/stock_rule.py
odoo/addons/so_line_description_picking/readme/CONTRIBUTORS.md
odoo/addons/so_line_description_picking/readme/DESCRIPTION.md
odoo/addons/so_line_description_picking/readme/USAGE.md
odoo/addons/so_line_description_picking/static/description/icon.png
odoo/addons/so_line_description_picking/static/description/index.html
odoo/addons/so_line_description_picking/tests/__init__.py
odoo/addons/so_line_description_picking/tests/test_so_line_description_picking.py
odoo/addons/so_line_description_picking/views/stock_picking_views.xml
odoo_addon_so_line_description_picking-15.0.1.0.0.1.dist-info/METADATA
odoo_addon_so_line_description_picking-15.0.1.0.0.1.dist-info/WHEEL
odoo_addon_so_line_description_picking-15.0.1.0.0.1.dist-info/top_level.txt
odoo_addon_so_line_description_picking-15.0.1.0.0.1.dist-info/RECORD
